pelican/plugins/tailwindcss/__init__.py
pelican/plugins/tailwindcss/package.json
pelican/plugins/tailwindcss/tailwindcss.py
pelican/plugins/tailwindcss/test_tailwindcss.py
pelican/plugins/tailwindcss/utils/__init__.py
pelican/plugins/tailwindcss/utils/commands.py
pelican/plugins/tailwindcss/utils/installs.py
pelican/plugins/tailwindcss/utils/utils.py
pelican_tailwindcss-0.3.0.dist-info/METADATA
pelican_tailwindcss-0.3.0.dist-info/WHEEL
pelican_tailwindcss-0.3.0.dist-info/entry_points.txt
pelican_tailwindcss-0.3.0.dist-info/RECORD
